setup.py
google_translator/GoogleConmunication.py
google_translator/Lang.py
google_translator/Translator.py
google_translator/__init__.py
google_translator.egg-info/PKG-INFO
google_translator.egg-info/SOURCES.txt
google_translator.egg-info/dependency_links.txt
google_translator.egg-info/top_level.txt