Metadata-Version: 1.1
Name: google-translator
Version: 0.1
Summary: google translate api
Home-page: https://github.com/lyrl/google_translator
Author: lyrl
Author-email: lyrl@me.com
License: MIT
Keywords: translate google
Platform: UNKNOWN
Classifier: Development Status :: 3 - Alpha
Classifier: Intended Audience :: Developers
Classifier: Topic :: Software Development :: Build Tools
Classifier: License :: OSI Approved :: MIT License
Classifier: Programming Language :: Python :: 2.7
